MANIFEST.in
README.md
setup.py
nlp/.DS_Store
nlp/MLmodel
nlp/Untitled.ipynb
nlp/conda.yaml
nlp/load_model_from_package.py
nltkPackage.egg-info/PKG-INFO
nltkPackage.egg-info/SOURCES.txt
nltkPackage.egg-info/dependency_links.txt
nltkPackage.egg-info/top_level.txt
nltkTransformer/LICENSE
nltkTransformer/NLTKWordPunctTokenizer.py
nltkTransformer/RegexSubstituter.py
nltkTransformer/RestrictedVocabTransformer.py
nltkTransformer/SentenceSplitter.py
nltkTransformer/SpellCheckTransformer.py
nltkTransformer/Untitled.ipynb
nltkTransformer/__init__.py
nltkTransformer/read_model.py